[
    {
        "name":"PC intel5 + 3060",
        "price":260000,
        "url":"../images/productosIMG/pc/pci512400f.png",
        "description":"Pc gamer Intel con una 3060",
        "categoria":"pc",
        "id":1,
        "stock":7

        
    },
    {
        "name":"PC intel7 + 3070",
        "price":360000,
        "url":"../images/productosIMG/pc/pci73070.png",
        "description":"Pc gamer Intel con una 3070",
        "categoria":"pc",
        "id":2,
        "stock":5
    },
    {
        "name":"PC intel7 + 3070",
        "price":3630000,
        "url":"../images/productosIMG/pc/pci7127003070.png",
        "description":"Pc gamer Intel con una 3070",
        "categoria":"pc",
        "id":3,
        "stock":6
        
    },
    {
        "name":"PC intel7 + 3080",
        "price":380000,
        "url":"../images/productosIMG/pc/pci73080.png",
        "description":"Pc gamer Intel con una 3080",
        "categoria":"pc",
        "id":4,
        "stock":2
    },
    {
        "name":"PC Ryzen5 + 6700XT",
        "price":365000,
        "url":"../images/productosIMG/pc/pcryzen5600rx6700.png",
        "description":"Pc gamer Ryzen con una 6700xt",
        "categoria":"pc",
        "id":5,
        "stock":4
    },
    {
        "name":"PC intel7 + 3080",
        "price":170000,
        "url":"../images/productosIMG/pc/pcryzen33400.png",
        "description":"Pc gamer Ryzen con graficos integrados",
        "categoria":"pc",
        "id":6,
        "stock":10
    },


    {
        "name":"Gabinete NZXT   ",
        "price":17000,
        "url":"../images/productosIMG/gabinetes/gabinete0.png",
        "description":"Gabinete Gamer",
        "categoria":"gabinete",
        "id":7,
        "stock":5
    },
    {
        "name":"Gabinete Xigmatek",
        "price":20000,
        "url":"../images/productosIMG/gabinetes/gabinete1.png",
        "description":"Gabinete Gamer",
        "categoria":"gabinete",
        "id":8,
        "stock":5
    },
    {
        "name":"Gabinete Xigmatek",
        "price":25000,
        "url":"../images/productosIMG/gabinetes/gabinete2.png",
        "description":"Gabinete Gamer",
        "categoria":"gabinete",
        "id":9,
        "stock":10
    },
    {
        "name":"Gabinete Medusa",
        "price":32000,
        "url":"../images/productosIMG/gabinetes/gabinete3.png",
        "description":"Gabinete Gamer",
        "categoria":"gabinete",
        "id":10,
        "stock":10
    },
    {
        "name":"Gabinete Kolink",
        "price":33000,
        "url":"../images/productosIMG/gabinetes/gabinete4.png",
        "description":"Gabinete Gamer",
        "categoria":"gabinete",
        "id":11,
        "stock":10
    },
    {
        "name":"Gabinete ROG ",
        "price":65000,
        "url":"../images/productosIMG/gabinetes/gabinete5.png",
        "description":"Gabinete Gamer",
        "categoria":"gabinete",
        "id":12,
        "stock":4
    },


    {
        "name":"Monitor Samsung",
        "price":45000,
        "url":"../images/productosIMG/monitores/Monitor1.png",
        "description":"Monitor Gamer",
        "categoria":"Monitor",
        "id":13,
        "stock":8
    },
    {
        "name":"Monitor Gigabyte",
        "price":35000,
        "url":"../images/productosIMG/monitores/Monitor2.png",
        "description":"Monitor Gamer",
        "categoria":"Monitor",
        "id":14,
        "stock":5
    },
    {
        "name":"Monitor ViewSonic",
        "price":38000,
        "url":"../images/productosIMG/monitores/Monitor3.png",
        "description":"Monitor Gamer",
        "categoria":"Monitor",
        "id":15,
        "stock":2
    },
    {
        "name":"Monitor TUF",
        "price":40000,
        "url":"../images/productosIMG/monitores/Monitor4.png",
        "description":"Monitor Gamer",
        "categoria":"Monitor",
        "id":16,
        "stock":3
    },
    {
        "name":"Monitor ViewSonic",
        "price":40000,
        "url":"../images/productosIMG/monitores/Monitor5.png",
        "description":"Monitor Gamer",
        "categoria":"Monitor",
        "id":17,
        "stock":10
    },
    {
        "name":"Monitor MSI",
        "price":50000,
        "url":"../images/productosIMG/monitores/Monitor6.png",
        "description":"Monitor Gamer",
        "categoria":"Monitor",
        "id":18,
        "stock":6
    },


    {
        "name":"Notebook Acer",
        "price":135000,
        "url":"../images/productosIMG/notebooks/acerI510300 8GB.png",
        "description":"Notebook Gamer",
        "categoria":"Notebook",
        "id":19,
        "stock":5
    },
    {
        "name":"Notebook Rog",
        "price":132000,
        "url":"../images/productosIMG/notebooks/asusrogI7 1070.png",
        "description":"Notebook Gamer",
        "categoria":"Notebook",
        "id":20,
        "stock":10
    },
    {
        "name":"Notebook Bangho",
        "price":185000,
        "url":"../images/productosIMG/notebooks/banghoi532gb.png",
        "description":"Notebook Gamer",
        "categoria":"Notebook",
        "id":21,
        "stock":7
    },
    {
        "name":"Notebook HP",
        "price":190000,
        "url":"../images/productosIMG/notebooks/hpi524gb.png",
        "description":"Notebook Gamer",
        "categoria":"Notebook",
        "id":22,
        "stock":5
    },
    {
        "name":"Notebook MSI",
        "price":305000,
        "url":"../images/productosIMG/notebooks/msi i5 8gb.png",
        "description":"Notebook Gamer",
        "categoria":"Notebook",
        "id":23,
        "stock":6
    },
    {
        "name":"Notebook MSI",
        "price":205000,
        "url":"../images/productosIMG/notebooks/msiR7 Rx6600.png",
        "description":"Notebook Gamer",
        "categoria":"Notebook",
        "id":24,
        "stock":10
    }
]